lfimap/__init__.py
lfimap/lfimap.py
lfimap/src/attacks/__init__.py
lfimap/src/attacks/bash.py
lfimap/src/attacks/cmdi.py
lfimap/src/attacks/data.py
lfimap/src/attacks/expect.py
lfimap/src/attacks/file.py
lfimap/src/attacks/filter.py
lfimap/src/attacks/heur.py
lfimap/src/attacks/input.py
lfimap/src/attacks/logPoison.py
lfimap/src/attacks/nc.py
lfimap/src/attacks/perl.py
lfimap/src/attacks/php.py
lfimap/src/attacks/powershell.py
lfimap/src/attacks/pwn.py
lfimap/src/attacks/rfi.py
lfimap/src/attacks/telnet.py
lfimap/src/attacks/trunc.py
lfimap/src/attacks/__pycache__/__init__.cpython-311.pyc
lfimap/src/attacks/__pycache__/bash.cpython-311.pyc
lfimap/src/attacks/__pycache__/cmdi.cpython-311.pyc
lfimap/src/attacks/__pycache__/data.cpython-311.pyc
lfimap/src/attacks/__pycache__/expect.cpython-311.pyc
lfimap/src/attacks/__pycache__/file.cpython-311.pyc
lfimap/src/attacks/__pycache__/filter.cpython-311.pyc
lfimap/src/attacks/__pycache__/heur.cpython-311.pyc
lfimap/src/attacks/__pycache__/input.cpython-311.pyc
lfimap/src/attacks/__pycache__/logPoison.cpython-311.pyc
lfimap/src/attacks/__pycache__/nc.cpython-311.pyc
lfimap/src/attacks/__pycache__/perl.cpython-311.pyc
lfimap/src/attacks/__pycache__/php.cpython-311.pyc
lfimap/src/attacks/__pycache__/powershell.cpython-311.pyc
lfimap/src/attacks/__pycache__/pwn.cpython-311.pyc
lfimap/src/attacks/__pycache__/rfi.cpython-311.pyc
lfimap/src/attacks/__pycache__/telnet.cpython-311.pyc
lfimap/src/attacks/__pycache__/trunc.cpython-311.pyc
lfimap/src/configs/__init__.py
lfimap/src/configs/config.py
lfimap/src/configs/__pycache__/__init__.cpython-311.pyc
lfimap/src/configs/__pycache__/config.cpython-311.pyc
lfimap/src/exploits/961bb08a95dbc34397248d92352da799
lfimap/src/exploits/__init__.py
lfimap/src/exploits/reverse_shell_lin.php
lfimap/src/exploits/reverse_shell_win.php
lfimap/src/exploits/ysvznc
lfimap/src/exploits/ysvznc.gif
lfimap/src/exploits/ysvznc.html
lfimap/src/exploits/ysvznc.jpg
lfimap/src/exploits/ysvznc.jsp
lfimap/src/lfimap.egg-info/PKG-INFO
lfimap/src/lfimap.egg-info/SOURCES.txt
lfimap/src/lfimap.egg-info/dependency_links.txt
lfimap/src/lfimap.egg-info/entry_points.txt
lfimap/src/lfimap.egg-info/requires.txt
lfimap/src/lfimap.egg-info/top_level.txt
lfimap-0.1.4.dist-info/LICENSE
lfimap-0.1.4.dist-info/METADATA
lfimap-0.1.4.dist-info/WHEEL
lfimap-0.1.4.dist-info/entry_points.txt
lfimap-0.1.4.dist-info/top_level.txt
lfimap-0.1.4.dist-info/RECORD
