Metadata-Version: 2.1
Name: lfimap
Version: 0.1.4
Summary: Local File Inclusion discovery and exploitation tool
Home-page: https://github.com/hansmach1ne/LFImap
Author: @h4nsmach1ne
Author-email: therealpowa@gmail.com
License: Apache
Classifier: Programming Language :: Python :: 3
Classifier: License :: OSI Approved :: Apache Software License
Classifier: Operating System :: OS Independent
License-File: LICENSE
Requires-Dist: argparse
Requires-Dist: bs4
Requires-Dist: pybase64
Requires-Dist: requests
Requires-Dist: urllib3
